open_constructs_aws_cdk/__init__.py
open_constructs_aws_cdk/py.typed
open_constructs_aws_cdk/_jsii/__init__.py
open_constructs_aws_cdk/_jsii/aws-cdk@0.1.2.jsii.tgz
open_constructs_aws_cdk/aws_codeartifact/__init__.py
open_constructs_aws_cdk/aws_cur/__init__.py
open_constructs_aws_cdk/aws_ec2/__init__.py
open_constructs_aws_cdk/aws_elasticache/__init__.py
open_constructs_aws_cdk/aws_fsx/__init__.py
open_constructs_aws_cdk/aws_redshiftserverless/__init__.py
open_constructs_aws_cdk-0.1.2.dist-info/LICENSE
open_constructs_aws_cdk-0.1.2.dist-info/METADATA
open_constructs_aws_cdk-0.1.2.dist-info/WHEEL
open_constructs_aws_cdk-0.1.2.dist-info/top_level.txt
open_constructs_aws_cdk-0.1.2.dist-info/RECORD
