Metadata-Version: 2.1
Name: open-constructs-aws-cdk
Version: 0.1.2
Summary: @open-constructs/aws-cdk
Home-page: https://github.com/open-constructs/aws-cdk-library.git
Author: Open Construct Foundation<thorsten.hoeger@taimos.de>
License: Apache-2.0
Project-URL: Source, https://github.com/open-constructs/aws-cdk-library.git
Classifier: Intended Audience :: Developers
Classifier: Operating System :: OS Independent
Classifier: Programming Language :: JavaScript
Classifier: Programming Language :: Python :: 3 :: Only
Classifier: Programming Language :: Python :: 3.8
Classifier: Programming Language :: Python :: 3.9
Classifier: Programming Language :: Python :: 3.10
Classifier: Programming Language :: Python :: 3.11
Classifier: Typing :: Typed
Classifier: Development Status :: 5 - Production/Stable
Classifier: License :: OSI Approved
Requires-Python: ~=3.8
License-File: LICENSE
Requires-Dist: aws-cdk-lib<3.0.0,>=2.168.0
Requires-Dist: constructs<11.0.0,>=10.3.0
Requires-Dist: jsii<2.0.0,>=1.106.0
Requires-Dist: publication>=0.0.3
Requires-Dist: typeguard<4.3.0,>=2.13.3
